migreat/MiGreat.py
migreat/__init__.py
migreat/bin/__init__.py
migreat/bin/migreat
migreat/bin/migreat.py
migreat/example/docker-compose.yml
migreat/example/svc1/Dockerfile
migreat/example/svc1/MiGreat.yaml
migreat/example/svc1/requirements.txt
migreat/example/svc1/versions/0001_create_user_table.py
migreat/example/svc1/versions/0002_create_enum_type.py
migreat/example/svc1/versions/0003_alter_enum_type.py
migreat/example/svc1/versions/0004_create_shared_table.py
migreat/example/svc2/Dockerfile
migreat/example/svc2/MiGreat.yaml
migreat/example/svc2/requirements.txt
migreat/example/svc2/start.sh
migreat/example/svc2/versions/0001_create_fun_table.py
migreat/templates/MiGreat.yaml
migreat/templates/migrator.tmpl
migreat_cli-0.2.9.dist-info/LICENSE
migreat_cli-0.2.9.dist-info/METADATA
migreat_cli-0.2.9.dist-info/WHEEL
migreat_cli-0.2.9.dist-info/entry_points.txt
migreat_cli-0.2.9.dist-info/RECORD
