Metadata-Version: 2.1
Name: MiGreat-cli
Version: 0.2.9
Summary: A schema isolated Postgres migrator for shared database micro services
License: MIT
Author: Flying Hashibuto
Author-email: hashibuto@noreply.com
Requires-Python: >=3.10,<4.0
Classifier: License :: OSI Approved :: MIT License
Classifier: Programming Language :: Python :: 3
Classifier: Programming Language :: Python :: 3.10
Classifier: Programming Language :: Python :: 3.11
Classifier: Programming Language :: Python :: 3.12
Requires-Dist: PyYAML (>=6.0.1,<7.0.0)
Requires-Dist: psycopg2-binary (>=2.9.9,<3.0.0)
Requires-Dist: pydantic (>=1.10.14,<2.0.0)
Requires-Dist: sqlalchemy (>=2.0.29,<3.0.0)
